Metadata-Version: 2.1
Name: pikli
Version: 1.0
Summary: A library to create cli apps
Home-page: https://github.com/Anondo/pikli
Author: Ahmad Anondo
Author-email: aanondos@gmail.com
License: UNKNOWN
Platform: UNKNOWN
Classifier: Programming Language :: Python :: 3
Classifier: License :: OSI Approved :: MIT License
Classifier: Operating System :: OS Independent
